media_summarizer/__init__.py
media_summarizer/main.py
media_summarizer/prompts.py
media_summarizer-2025.12.21160330.dist-info/METADATA
media_summarizer-2025.12.21160330.dist-info/WHEEL
media_summarizer-2025.12.21160330.dist-info/top_level.txt
media_summarizer-2025.12.21160330.dist-info/RECORD
