Metadata-Version: 2.4
Name: media-summarizer
Version: 2025.12.21160330
Summary: A new package designed to interpret and summarize user-provided textual descriptions of multimedia content, such as videos or audio transcripts, to generate structured overviews or insights. It allows
Author-email: media-summarizer <hi@eugene.plus>
License: MIT
Project-URL: Homepage, https://github.com/chigwell/media-summarizer
Requires-Python: >=3.9
Requires-Dist: langchain-llm7>=0.0.0
Requires-Dist: llmatch-messages>=0.0.0
Requires-Dist: langchain-core>=0.3.0
